{"cameraMode":{"drawMode":0,"name":"Shaded","section":"Shading Mode"},"sceneLighting":true,"audioPlay":false,"sceneViewState":{"m_AlwaysRefresh":false,"showFog":true,"showSkybox":true,"showFlares":true,"showImageEffects":true,"showParticleSystems":true,"showVisualEffectGraphs":true,"m_FxEnabled":true},"in2DMode":false,"pivot":{"x":1.8331853151321412,"y":-53.290733337402347,"z":44.38827133178711},"rotation":{"x":0.3957235813140869,"y":-0.07564618438482285,"z":0.03274424001574516,"w":0.9147117733955383},"size":57.736473083496097,"orthographic":false}